jk_smallgraph/DirectedGraph.py
jk_smallgraph/ILink.py
jk_smallgraph/INode.py
jk_smallgraph/Link.py
jk_smallgraph/Node.py
jk_smallgraph/__init__.py
jk_smallgraph/io/GraphvizIO.py
jk_smallgraph/io/SimpleEdgeListIO.py
jk_smallgraph/io/__init__.py
jk_smallgraph-0.2024.5.25.dist-info/WHEEL
jk_smallgraph-0.2024.5.25.dist-info/METADATA
jk_smallgraph-0.2024.5.25.dist-info/RECORD
