Metadata-Version: 2.1
Name: jk_smallgraph
Version: 0.2024.5.25
Summary: A directed graph implementation where each node and link is represented as an individual object.
Keywords: graph
Author-email: Jürgen Knauth <pubsrc@binary-overflow.de>
Maintainer-email: Jürgen Knauth <pubsrc@binary-overflow.de>
Requires-Python: >=3.8
Classifier: Development Status :: 5 - Production/Stable
Classifier: License :: OSI Approved :: Apache Software License
Classifier: Programming Language :: Python :: 3
